{
  "lastUpdated": "2026-05-27",
  "note": "Auto-refreshed by RSS aggregator (free-tier backup).",
  "items": [
    {
      "title": "The In-Between Worlds of Larissa Borteh",
      "url": "https://hyperallergic.com/the-in-between-worlds-of-larissa-borteh/",
      "source": "Hyperallergic",
      "date": "2026-05-26",
      "summary": "In the artist's paintings, are we looking at plants in a state of beautiful decay, ghosts, deities, fairylands, or something from a dream?"
    },
    {
      "title": "Trump Re-Erects Monument of Enslaver Removed in 2020",
      "url": "https://hyperallergic.com/trump-re-erects-monument-of-enslaver-removed-in-2020/",
      "source": "Hyperallergic",
      "date": "2026-05-26",
      "summary": "The statue of Caesar Rodney, a signer of the Declaration of Independence who enslaved at least 200 people, is now on display in DC's Freedom Plaza."
    },
    {
      "title": "It's Art-World Summer in NYC",
      "url": "https://hyperallergic.com/its-art-world-summer-in-nyc/",
      "source": "Hyperallergic",
      "date": "2026-05-26",
      "summary": "Celebrate with a visit to Betye Saar's doll collection and Roberto Lugo's ode to Puerto Rico."
    },
    {
      "title": "Miami Graffiti Legend Eric Alan Hirt \"Eson\" Killed in Train Strike",
      "url": "https://hyperallergic.com/miami-graffiti-legend-eric-alan-hirt-eson-killed-in-train-strike/",
      "source": "Hyperallergic",
      "date": "2026-05-26",
      "summary": "The prolific tagger boldly transformed the city's street infrastructure for decades."
    }
  ]
}
